{
	"info": {
		"_postman_id": "e9a8d057-f68b-4b98-9f76-2159166359e0",
		"name": "Weather Map app",
		"schema": "https://schema.getpostman.com/json/collection/v2.1.0/collection.json",
		"_exporter_id": "19188117",
		"_collection_link": "https://bold-resonance-706397.postman.co/workspace/Supplier-Prism~b7eae6e0-9b09-499c-9891-d95dd8aaab77/collection/19188117-e9a8d057-f68b-4b98-9f76-2159166359e0?action=share&source=collection_link&creator=19188117"
	},
	"item": [
		{
			"name": "get weather",
			"request": {
				"method": "GET",
				"header": [],
				"url": {
					"raw": "http://127.0.0.1:8000/api/weather/",
					"protocol": "http",
					"host": [
						"127",
						"0",
						"0",
						"1"
					],
					"port": "8000",
					"path": [
						"api",
						"weather",
						""
					]
				}
			},
			"response": []
		},
		{
			"name": "get weather for a city ID",
			"request": {
				"method": "GET",
				"header": [],
				"url": {
					"raw": "http://127.0.0.1:8000/api/weather/1/",
					"protocol": "http",
					"host": [
						"127",
						"0",
						"0",
						"1"
					],
					"port": "8000",
					"path": [
						"api",
						"weather",
						"1",
						""
					]
				}
			},
			"response": []
		},
		{
			"name": "get weather for a city name",
			"request": {
				"method": "GET",
				"header": [],
				"url": {
					"raw": "http://127.0.0.1:8000/api/weather/London/",
					"protocol": "http",
					"host": [
						"127",
						"0",
						"0",
						"1"
					],
					"port": "8000",
					"path": [
						"api",
						"weather",
						"London",
						""
					]
				}
			},
			"response": []
		},
		{
			"name": "update weather for a city",
			"request": {
				"method": "PUT",
				"header": [],
				"body": {
					"mode": "raw",
					"raw": "{\r\n  \"temperature\": 20.0,\r\n  \"description\": \"Partly cloudy\",\r\n  \"city\":\"London\"\r\n}\r\n",
					"options": {
						"raw": {
							"language": "json"
						}
					}
				},
				"url": {
					"raw": "http://127.0.0.1:8000/api/weather/1/",
					"protocol": "http",
					"host": [
						"127",
						"0",
						"0",
						"1"
					],
					"port": "8000",
					"path": [
						"api",
						"weather",
						"1",
						""
					]
				}
			},
			"response": []
		},
		{
			"name": "delete weather for a city",
			"request": {
				"method": "DELETE",
				"header": [],
				"body": {
					"mode": "raw",
					"raw": "{\r\n  \"temperature\": 16.0,\r\n  \"description\": \"Partly cloudy\"\r\n}\r\n",
					"options": {
						"raw": {
							"language": "json"
						}
					}
				},
				"url": {
					"raw": "http://127.0.0.1:8000/api/weather/5/",
					"protocol": "http",
					"host": [
						"127",
						"0",
						"0",
						"1"
					],
					"port": "8000",
					"path": [
						"api",
						"weather",
						"5",
						""
					]
				}
			},
			"response": []
		},
		{
			"name": "store weather data for city",
			"request": {
				"method": "POST",
				"header": [],
				"url": {
					"raw": "http://127.0.0.1:8000/api/weather/fetch/New York/",
					"protocol": "http",
					"host": [
						"127",
						"0",
						"0",
						"1"
					],
					"port": "8000",
					"path": [
						"api",
						"weather",
						"fetch",
						"New York",
						""
					]
				}
			},
			"response": []
		}
	]
}